ares/__init__.py
ares/__main__.py
ares/baseline.py
ares/generator.py
ares/llm.py
ares/problems.py
ares/search.py
ares/verifier.py
ares_reasoning-1.0.0.dist-info/METADATA
ares_reasoning-1.0.0.dist-info/WHEEL
ares_reasoning-1.0.0.dist-info/entry_points.txt
ares_reasoning-1.0.0.dist-info/top_level.txt
ares_reasoning-1.0.0.dist-info/RECORD
