Metadata-Version: 2.4
Name: ares-reasoning
Version: 1.0.0
Summary: Inference-time reasoning framework that improves LLM accuracy through search and verification
Author: ARES Team
License: MIT
Project-URL: Homepage, https://github.com/yourusername/ares
Project-URL: Documentation, https://github.com/yourusername/ares#readme
Project-URL: Repository, https://github.com/yourusername/ares
Keywords: llm,reasoning,inference,search,verification,ai
Classifier: Development Status :: 4 - Beta
Classifier: Intended Audience :: Developers
Classifier: Intended Audience :: Science/Research
Classifier: License :: OSI Approved :: MIT License
Classifier: Programming Language :: Python :: 3
Classifier: Programming Language :: Python :: 3.8
Classifier: Programming Language :: Python :: 3.9
Classifier: Programming Language :: Python :: 3.10
Classifier: Programming Language :: Python :: 3.11
Classifier: Programming Language :: Python :: 3.12
Classifier: Topic :: Scientific/Engineering :: Artificial Intelligence
Requires-Python: >=3.8
Requires-Dist: requests>=2.28.0
Requires-Dist: python-dotenv>=1.0.0
Provides-Extra: dev
Requires-Dist: pytest>=7.0.0; extra == "dev"
Requires-Dist: black>=23.0.0; extra == "dev"
